main.py
setup.py
DecompOpt.egg-info/PKG-INFO
DecompOpt.egg-info/SOURCES.txt
DecompOpt.egg-info/dependency_links.txt
DecompOpt.egg-info/requires.txt
DecompOpt.egg-info/top_level.txt